tempo4d/__init__.py
tempo4d/bf_image.py
tempo4d/data_manager.py
tempo4d/data_process.py
tempo4d/data_process_gauss.py
tempo4d/qt14_corrected.py
tempo4d/strain_analysis_post3.py
tempo4d/models/__init__.py
tempo4d/models/yolov8_weights.pt
tempo4d/utils/__init__.py
tempo4d/utils/auto_cc_norm_batch_log2.py
tempo4d/utils/data_reader.py
tempo4d/utils/dspacing_batch5.py
tempo4d/utils/fit_index_batch2.py
tempo4d/utils/loadtxt3.py
tempo4d/utils/padding.py
tempo4d/utils/savetxt2.py
tempo4d/utils/strain_clean.py
tempo4d-0.1.8.dist-info/METADATA
tempo4d-0.1.8.dist-info/WHEEL
tempo4d-0.1.8.dist-info/top_level.txt
tempo4d-0.1.8.dist-info/RECORD
